compath/__init__.py
compath/__main__.py
compath/cli.py
compath/constants.py
compath/forms.py
compath/manager.py
compath/models.py
compath/utils.py
compath/web.py
compath/curation/__init__.py
compath/curation/hierarchies.py
compath/curation/parser.py
compath/curation/utils.py
compath/static/css/clustergrammer.css
compath/static/css/graph_explorer.css
compath/static/css/nav.css
compath/static/img/EFPIA_logo.jpg
compath/static/img/aetionomy_logo.png
compath/static/img/compath-blackbg-logo-1000px.png
compath/static/img/compath-logo-1000px.png
compath/static/img/compath-logo-100px.png
compath/static/img/eu_logo.png
compath/static/img/imi_logo.png
compath/static/img/scai_logo.svg
compath/static/img/gif/loading.gif
compath/static/js/graph_controller.js
compath/static/js/mapping_landscape.js
compath/static/js/overlap_controller.js
compath/static/js/pathway_controller.js
compath/static/js/pathway_knowledge_graph_controller.js
compath/static/js/dependencies/clustergrammer.js
compath/static/js/dependencies/cola.js
compath/static/js/dependencies/cytoscape-gtip.js
compath/static/js/dependencies/venn.js
compath/static/json/cy-style.json
compath/static/json/kegg_clustergrammer.json
compath/static/json/reactome_clustergrammer.json
compath/static/json/wikipathways_clustergrammer.json
compath/static/json/all/kegg_reactome_10.json
compath/static/json/all/kegg_reactome_100.json
compath/static/json/all/kegg_reactome_20.json
compath/static/json/all/kegg_reactome_30.json
compath/static/json/all/kegg_reactome_40.json
compath/static/json/all/kegg_reactome_50.json
compath/static/json/all/kegg_reactome_60.json
compath/static/json/all/kegg_reactome_70.json
compath/static/json/all/kegg_reactome_80.json
compath/static/json/all/kegg_reactome_90.json
compath/static/json/all/kegg_wikipathways_10.json
compath/static/json/all/kegg_wikipathways_100.json
compath/static/json/all/kegg_wikipathways_20.json
compath-0.1.0.dist-info/METADATA
compath-0.1.0.dist-info/RECORD
compath-0.1.0.dist-info/WHEEL
compath-0.1.0.dist-info/entry_points.txt
compath-0.1.0.dist-info/top_level.txt
