Metadata-Version: 2.1
Name: compath
Version: 0.1.0
Summary: A web application for exploring and comparing the overlaps across pathway resources
Home-page: https://github.com/ComPath/ComPath
Author: Daniel Domingo-Fernández and Charles Tapley Hoyt
Author-email: daniel.domingo.fernandez@scai.fraunhofer.de
Maintainer: Daniel Domingo-Fernández and Charles Tapley Hoyt
Maintainer-email: daniel.domingo.fernandez@scai.fraunhofer.de
License: MIT License
Keywords: Pathways,Systems Biology,Networks Biology
Platform: UNKNOWN
Classifier: Development Status :: 4 - Beta
Classifier: Environment :: Console
Classifier: Intended Audience :: Developers
Classifier: Intended Audience :: Science/Research
Classifier: License :: OSI Approved :: MIT License
Classifier: Operating System :: OS Independent
Classifier: Programming Language :: Python
Classifier: Programming Language :: Python :: 3.6
Classifier: Topic :: Scientific/Engineering :: Bio-Informatics
Requires-Dist: click
Requires-Dist: sqlalchemy
Requires-Dist: bio2bel (>=0.1.0)
Requires-Dist: compath-utils (>=0.1.0)
Requires-Dist: bio2bel-hgnc (>=0.1.0)
Requires-Dist: wtforms
Requires-Dist: flask-wtf
Requires-Dist: flask
Requires-Dist: flask-bootstrap
Requires-Dist: flask-admin
Requires-Dist: flask-security
Requires-Dist: flask-sqlalchemy
Requires-Dist: networkx (==1.11)
Requires-Dist: pandas
Requires-Dist: scipy
Requires-Dist: tqdm
Requires-Dist: numpy
Requires-Dist: statsmodels
Requires-Dist: xlrd
